pollination/ladybug_comfort/__init__.py
pollination/ladybug_comfort/epw.py
pollination/ladybug_comfort/map.py
pollination/ladybug_comfort/mtx.py
pollination_ladybug_comfort-0.5.6.dist-info/LICENSE
pollination_ladybug_comfort-0.5.6.dist-info/METADATA
pollination_ladybug_comfort-0.5.6.dist-info/WHEEL
pollination_ladybug_comfort-0.5.6.dist-info/top_level.txt
pollination_ladybug_comfort-0.5.6.dist-info/RECORD
